pyinmem/__init__.py
pyinmem/core.py
pyinmem/exceptions.py
pyinmem/server.py
pyinmem/strategy/__init__.py
pyinmem/strategy/base.py
pyinmem/strategy/list.py
pyinmem/strategy/set.py
pyinmem/strategy/sorted_set.py
pyinmem/strategy/string.py
pyinmem-1.dist-info/METADATA
pyinmem-1.dist-info/WHEEL
pyinmem-1.dist-info/RECORD
