Metadata-Version: 2.1
Name: pyinmem
Version: 1
Summary: Python in-memory database
Author: Your Name
Author-email: you@example.com
Requires-Python: >=3.11,<4.0
Classifier: Programming Language :: Python :: 3
Classifier: Programming Language :: Python :: 3.11
Classifier: Programming Language :: Python :: 3.12
Requires-Dist: coverage (>=7.4.2,<8.0.0)
Requires-Dist: poetry (>=1.7.1,<2.0.0)
Requires-Dist: pytest (>=8.0.1,<9.0.0)
Requires-Dist: pytest-cov (>=4.1.0,<5.0.0)
